meteoblue_dataset_sdk/__init__.py
meteoblue_dataset_sdk/client.py
meteoblue_dataset_sdk/utils.py
meteoblue_dataset_sdk/caching/__init__.py
meteoblue_dataset_sdk/caching/abstractcache.py
meteoblue_dataset_sdk/caching/filecache.py
meteoblue_dataset_sdk/protobuf/__init__.py
meteoblue_dataset_sdk/protobuf/dataset.proto
meteoblue_dataset_sdk/protobuf/dataset_pb2.py
meteoblue_dataset_sdk/protobuf/measurements.proto
meteoblue_dataset_sdk/protobuf/measurements_pb2.py
tests/__init__.py
tests/test_cache.py
tests/test_measurement_query.py
tests/test_query.py
meteoblue_dataset_sdk-1.3.5.dist-info/LICENSE
meteoblue_dataset_sdk-1.3.5.dist-info/METADATA
meteoblue_dataset_sdk-1.3.5.dist-info/WHEEL
meteoblue_dataset_sdk-1.3.5.dist-info/top_level.txt
meteoblue_dataset_sdk-1.3.5.dist-info/RECORD
