Metadata-Version: 2.2
Name: meteoblue_dataset_sdk
Version: 1.3.5
Summary: Easy access to the meteoblue dataset API
Home-page: https://github.com/meteoblue/python-dataset-sdk
Author: meteoblue AG
Author-email: patrick.zippenfenig@meteoblue.com
License: MIT License
Keywords: meteoblue
Classifier: Programming Language :: Python :: 3
Classifier: License :: OSI Approved :: MIT License
Requires-Python: >=3.9
License-File: LICENSE
Requires-Dist: aiohttp<4,>=3.9.5
Requires-Dist: protobuf<6,>=5.27.1
Requires-Dist: aiofiles<25,>=24.1.0
Provides-Extra: dev
Requires-Dist: pytest; extra == "dev"
Requires-Dist: flake8; extra == "dev"
Requires-Dist: ipython; extra == "dev"
Requires-Dist: nox; extra == "dev"
Requires-Dist: black; extra == "dev"
Requires-Dist: isort; extra == "dev"
Requires-Dist: freezegun; extra == "dev"
Requires-Dist: later; extra == "dev"
Requires-Dist: pandas; extra == "dev"
Requires-Dist: matplotlib; extra == "dev"
